PokerLibSim/Cards.py
PokerLibSim/TestingLogic.py
PokerLibSim/__init__.py
pokerlibsim-0.1.dist-info/licenses/LICENSE
tests/__init__.py
tests/test_Cards.py
pokerlibsim-0.1.dist-info/METADATA
pokerlibsim-0.1.dist-info/WHEEL
pokerlibsim-0.1.dist-info/top_level.txt
pokerlibsim-0.1.dist-info/RECORD
