Metadata-Version: 2.4
Name: PokerLibSim
Version: 0.1
Summary: A simple Python poker library for card and hand evaluation for easy simulation and strategy development
Home-page: https://github.com/Nuffa1/PokerLib
Author: Nyel Uffa
Author-email: nyeluffa1@gmail.com
Requires-Python: >=3.7
License-File: LICENSE
Dynamic: author
Dynamic: author-email
Dynamic: home-page
Dynamic: license-file
Dynamic: requires-python
Dynamic: summary
